<?xml version="1.0" encoding="UTF-8"?>
<launch4jConfig>
  <dontWrapJar>true</dontWrapJar>
  <headerType>gui</headerType>
  <jar>launcher-bootstrap.jar</jar>
  <outfile>resources/launcher.exe</outfile>
  <errTitle>MCJE Launcher</errTitle>
  <cmdLine></cmdLine>
  <chdir>.</chdir>
  <priority>normal</priority>
  <downloadUrl>https://adoptium.net/</downloadUrl>
  <supportUrl>https://mcje-bucket.sfo3.digitaloceanspaces.com/</supportUrl>
  <stayAlive>false</stayAlive>
  <restartOnCrash>false</restartOnCrash>
  <manifest></manifest>
  <icon>resources/icon.ico</icon>
  <jre>
    <path>jre</path>
    <bundledJre64Bit>true</bundledJre64Bit>
    <bundledJreAsFallback>false</bundledJreAsFallback>
    <minVersion>21</minVersion>
    <maxVersion></maxVersion>
    <jdkPreference>preferJre</jdkPreference>
    <runtimeBits>64</runtimeBits>
  </jre>
  <versionInfo>
    <fileVersion>1.0.0.0</fileVersion>
    <txtFileVersion>1.0.0</txtFileVersion>
    <fileDescription>MCJE Minecraft Launcher</fileDescription>
    <copyright>MCJE</copyright>
    <productVersion>1.0.0.0</productVersion>
    <txtProductVersion>1.0.0</txtProductVersion>
    <productName>MCJE Launcher</productName>
    <companyName>MCJE</companyName>
    <internalName>MCJELauncher</internalName>
    <originalFilename>MCJE Launcher.exe</originalFilename>
    <trademarks></trademarks>
    <language>ENGLISH_US</language>
  </versionInfo>
</launch4jConfig>
